esther_lotto/__init__.py
esther_lotto/draw.py
esther_lotto-0.2.1.dist-info/METADATA
esther_lotto-0.2.1.dist-info/WHEEL
esther_lotto-0.2.1.dist-info/top_level.txt
esther_lotto-0.2.1.dist-info/RECORD
